codonlib/__init__.py
codonlib/cli.py
codonlib/codon.py
codonlib/codonlib.py
codonlib-0.1.0.dist-info/AUTHORS.rst
codonlib-0.1.0.dist-info/LICENSE
codonlib-0.1.0.dist-info/METADATA
codonlib-0.1.0.dist-info/WHEEL
codonlib-0.1.0.dist-info/entry_points.txt
codonlib-0.1.0.dist-info/top_level.txt
codonlib-0.1.0.dist-info/RECORD
