Metadata-Version: 2.1
Name: codonlib
Version: 0.1.0
Summary: Codon Degeneracy
Home-page: https://github.com/tmsincomb/codonlib
Author: Troy Sincomb
Author-email: tsincomb@gmail.com
License: MIT license
Keywords: codonlib
Platform: UNKNOWN
Classifier: Development Status :: 2 - Pre-Alpha
Classifier: Intended Audience :: Developers
Classifier: License :: OSI Approved :: MIT License
Classifier: Natural Language :: English
Classifier: Programming Language :: Python :: 3
Classifier: Programming Language :: Python :: 3.6
Classifier: Programming Language :: Python :: 3.7
Classifier: Programming Language :: Python :: 3.8
Classifier: Programming Language :: Python :: 3.9
Requires-Python: >=3.6
License-File: LICENSE
License-File: AUTHORS.rst
Requires-Dist: Click (>=7.0)
